Authors.txt
ChangeLog.txt
LICENSE.txt
MANIFEST.in
Makefile
README.md
example.pkgs
pmcyg.py
pyproject.toml
setup.py
pmcyg/__init__.py
pmcyg/apptools.py
pmcyg/command_line.py
pmcyg/core.py
pmcyg/gui.py
pmcyg/gui_imgs.py
pmcyg/version.py
pmcyg.egg-info/PKG-INFO
pmcyg.egg-info/SOURCES.txt
pmcyg.egg-info/dependency_links.txt
pmcyg.egg-info/entry_points.txt
pmcyg.egg-info/top_level.txt
test/testPMCyg.py