Metadata-Version: 1.1
Name: pmcyg
Version: 3.2.0
Summary: Utility for creating offline Cygwin installers
Home-page: https://github.com/rwpenney/pmcyg
Author: RW Penney
Author-email: rwpenney@users.sourceforge.net
License: GPL v3
Download-URL: https://github.com/rwpenney/pmcyg/archive/pmcyg-3.2.0.tar.gz
Keywords: Cygwin
Platform: UNKNOWN
Classifier: Programming Language :: Python :: 3
Classifier: Topic :: Utilities
